<?xml version="1.0" encoding="UTF-8" standalone="yes"?>
<w:webSettings xmlns:mc="http://schemas.openxmlformats.org/markup-compatibility/2006" xmlns:r="http://schemas.openxmlformats.org/officeDocument/2006/relationships" xmlns:w="http://schemas.openxmlformats.org/wordprocessingml/2006/main" xmlns:w14="http://schemas.microsoft.com/office/word/2010/wordml" xmlns:w15="http://schemas.microsoft.com/office/word/2012/wordml" mc:Ignorable="w14 w15"><w:divs><w:div w:id="242186789"><w:bodyDiv w:val="1"/><w:marLeft w:val="0"/><w:marRight w:val="0"/><w:marTop w:val="0"/><w:marBottom w:val="0"/><w:divBdr><w:top w:val="none" w:sz="0" w:space="0" w:color="auto"/><w:left w:val="none" w:sz="0" w:space="0" w:color="auto"/><w:bottom w:val="none" w:sz="0" w:space="0" w:color="auto"/><w:right w:val="none" w:sz="0" w:space="0" w:color="auto"/></w:divBdr><w:divsChild><w:div w:id="493490377"><w:marLeft w:val="360"/><w:marRight w:val="0"/><w:marTop w:val="200"/><w:marBottom w:val="0"/><w:divBdr><w:top w:val="none" w:sz="0" w:space="0" w:color="auto"/><w:left w:val="none" w:sz="0" w:space="0" w:color="auto"/><w:bottom w:val="none" w:sz="0" w:space="0" w:color="auto"/><w:right w:val="none" w:sz="0" w:space="0" w:color="auto"/></w:divBdr></w:div></w:divsChild></w:div><w:div w:id="242642041"><w:bodyDiv w:val="1"/><w:marLeft w:val="0"/><w:marRight w:val="0"/><w:marTop w:val="0"/><w:marBottom w:val="0"/><w:divBdr><w:top w:val="none" w:sz="0" w:space="0" w:color="auto"/><w:left w:val="none" w:sz="0" w:space="0" w:color="auto"/><w:bottom w:val="none" w:sz="0" w:space="0" w:color="auto"/><w:right w:val="none" w:sz="0" w:space="0" w:color="auto"/></w:divBdr><w:divsChild><w:div w:id="2141531333"><w:marLeft w:val="360"/><w:marRight w:val="0"/><w:marTop w:val="200"/><w:marBottom w:val="160"/><w:divBdr><w:top w:val="none" w:sz="0" w:space="0" w:color="auto"/><w:left w:val="none" w:sz="0" w:space="0" w:color="auto"/><w:bottom w:val="none" w:sz="0" w:space="0" w:color="auto"/><w:right w:val="none" w:sz="0" w:space="0" w:color="auto"/></w:divBdr></w:div></w:divsChild></w:div><w:div w:id="261378378"><w:bodyDiv w:val="1"/><w:marLeft w:val="0"/><w:marRight w:val="0"/><w:marTop w:val="0"/><w:marBottom w:val="0"/><w:divBdr><w:top w:val="none" w:sz="0" w:space="0" w:color="auto"/><w:left w:val="none" w:sz="0" w:space="0" w:color="auto"/><w:bottom w:val="none" w:sz="0" w:space="0" w:color="auto"/><w:right w:val="none" w:sz="0" w:space="0" w:color="auto"/></w:divBdr></w:div><w:div w:id="525414498"><w:bodyDiv w:val="1"/><w:marLeft w:val="0"/><w:marRight w:val="0"/><w:marTop w:val="0"/><w:marBottom w:val="0"/><w:divBdr><w:top w:val="none" w:sz="0" w:space="0" w:color="auto"/><w:left w:val="none" w:sz="0" w:space="0" w:color="auto"/><w:bottom w:val="none" w:sz="0" w:space="0" w:color="auto"/><w:right w:val="none" w:sz="0" w:space="0" w:color="auto"/></w:divBdr><w:divsChild><w:div w:id="1559125710"><w:marLeft w:val="360"/><w:marRight w:val="0"/><w:marTop w:val="200"/><w:marBottom w:val="160"/><w:divBdr><w:top w:val="none" w:sz="0" w:space="0" w:color="auto"/><w:left w:val="none" w:sz="0" w:space="0" w:color="auto"/><w:bottom w:val="none" w:sz="0" w:space="0" w:color="auto"/><w:right w:val="none" w:sz="0" w:space="0" w:color="auto"/></w:divBdr></w:div></w:divsChild></w:div><w:div w:id="608468546"><w:bodyDiv w:val="1"/><w:marLeft w:val="0"/><w:marRight w:val="0"/><w:marTop w:val="0"/><w:marBottom w:val="0"/><w:divBdr><w:top w:val="none" w:sz="0" w:space="0" w:color="auto"/><w:left w:val="none" w:sz="0" w:space="0" w:color="auto"/><w:bottom w:val="none" w:sz="0" w:space="0" w:color="auto"/><w:right w:val="none" w:sz="0" w:space="0" w:color="auto"/></w:divBdr></w:div><w:div w:id="612439323"><w:bodyDiv w:val="1"/><w:marLeft w:val="0"/><w:marRight w:val="0"/><w:marTop w:val="0"/><w:marBottom w:val="0"/><w:divBdr><w:top w:val="none" w:sz="0" w:space="0" w:color="auto"/><w:left w:val="none" w:sz="0" w:space="0" w:color="auto"/><w:bottom w:val="none" w:sz="0" w:space="0" w:color="auto"/><w:right w:val="none" w:sz="0" w:space="0" w:color="auto"/></w:divBdr><w:divsChild><w:div w:id="1449082181"><w:marLeft w:val="360"/><w:marRight w:val="0"/><w:marTop w:val="200"/><w:marBottom w:val="0"/><w:divBdr><w:top w:val="none" w:sz="0" w:space="0" w:color="auto"/><w:left w:val="none" w:sz="0" w:space="0" w:color="auto"/><w:bottom w:val="none" w:sz="0" w:space="0" w:color="auto"/><w:right w:val="none" w:sz="0" w:space="0" w:color="auto"/></w:divBdr></w:div></w:divsChild></w:div><w:div w:id="819887796"><w:bodyDiv w:val="1"/><w:marLeft w:val="0"/><w:marRight w:val="0"/><w:marTop w:val="0"/><w:marBottom w:val="0"/><w:divBdr><w:top w:val="none" w:sz="0" w:space="0" w:color="auto"/><w:left w:val="none" w:sz="0" w:space="0" w:color="auto"/><w:bottom w:val="none" w:sz="0" w:space="0" w:color="auto"/><w:right w:val="none" w:sz="0" w:space="0" w:color="auto"/></w:divBdr><w:divsChild><w:div w:id="450393187"><w:marLeft w:val="360"/><w:marRight w:val="0"/><w:marTop w:val="200"/><w:marBottom w:val="160"/><w:divBdr><w:top w:val="none" w:sz="0" w:space="0" w:color="auto"/><w:left w:val="none" w:sz="0" w:space="0" w:color="auto"/><w:bottom w:val="none" w:sz="0" w:space="0" w:color="auto"/><w:right w:val="none" w:sz="0" w:space="0" w:color="auto"/></w:divBdr></w:div></w:divsChild></w:div><w:div w:id="1211921238"><w:bodyDiv w:val="1"/><w:marLeft w:val="0"/><w:marRight w:val="0"/><w:marTop w:val="0"/><w:marBottom w:val="0"/><w:divBdr><w:top w:val="none" w:sz="0" w:space="0" w:color="auto"/><w:left w:val="none" w:sz="0" w:space="0" w:color="auto"/><w:bottom w:val="none" w:sz="0" w:space="0" w:color="auto"/><w:right w:val="none" w:sz="0" w:space="0" w:color="auto"/></w:divBdr><w:divsChild><w:div w:id="2083139926"><w:marLeft w:val="360"/><w:marRight w:val="0"/><w:marTop w:val="200"/><w:marBottom w:val="160"/><w:divBdr><w:top w:val="none" w:sz="0" w:space="0" w:color="auto"/><w:left w:val="none" w:sz="0" w:space="0" w:color="auto"/><w:bottom w:val="none" w:sz="0" w:space="0" w:color="auto"/><w:right w:val="none" w:sz="0" w:space="0" w:color="auto"/></w:divBdr></w:div></w:divsChild></w:div><w:div w:id="1278097736"><w:bodyDiv w:val="1"/><w:marLeft w:val="0"/><w:marRight w:val="0"/><w:marTop w:val="0"/><w:marBottom w:val="0"/><w:divBdr><w:top w:val="none" w:sz="0" w:space="0" w:color="auto"/><w:left w:val="none" w:sz="0" w:space="0" w:color="auto"/><w:bottom w:val="none" w:sz="0" w:space="0" w:color="auto"/><w:right w:val="none" w:sz="0" w:space="0" w:color="auto"/></w:divBdr><w:divsChild><w:div w:id="427774306"><w:marLeft w:val="360"/><w:marRight w:val="0"/><w:marTop w:val="200"/><w:marBottom w:val="0"/><w:divBdr><w:top w:val="none" w:sz="0" w:space="0" w:color="auto"/><w:left w:val="none" w:sz="0" w:space="0" w:color="auto"/><w:bottom w:val="none" w:sz="0" w:space="0" w:color="auto"/><w:right w:val="none" w:sz="0" w:space="0" w:color="auto"/></w:divBdr></w:div></w:divsChild></w:div><w:div w:id="1360474316"><w:bodyDiv w:val="1"/><w:marLeft w:val="0"/><w:marRight w:val="0"/><w:marTop w:val="0"/><w:marBottom w:val="0"/><w:divBdr><w:top w:val="none" w:sz="0" w:space="0" w:color="auto"/><w:left w:val="none" w:sz="0" w:space="0" w:color="auto"/><w:bottom w:val="none" w:sz="0" w:space="0" w:color="auto"/><w:right w:val="none" w:sz="0" w:space="0" w:color="auto"/></w:divBdr></w:div><w:div w:id="1505514323"><w:bodyDiv w:val="1"/><w:marLeft w:val="0"/><w:marRight w:val="0"/><w:marTop w:val="0"/><w:marBottom w:val="0"/><w:divBdr><w:top w:val="none" w:sz="0" w:space="0" w:color="auto"/><w:left w:val="none" w:sz="0" w:space="0" w:color="auto"/><w:bottom w:val="none" w:sz="0" w:space="0" w:color="auto"/><w:right w:val="none" w:sz="0" w:space="0" w:color="auto"/></w:divBdr><w:divsChild><w:div w:id="44329473"><w:marLeft w:val="360"/><w:marRight w:val="0"/><w:marTop w:val="200"/><w:marBottom w:val="160"/><w:divBdr><w:top w:val="none" w:sz="0" w:space="0" w:color="auto"/><w:left w:val="none" w:sz="0" w:space="0" w:color="auto"/><w:bottom w:val="none" w:sz="0" w:space="0" w:color="auto"/><w:right w:val="none" w:sz="0" w:space="0" w:color="auto"/></w:divBdr></w:div></w:divsChild></w:div><w:div w:id="1578441052"><w:bodyDiv w:val="1"/><w:marLeft w:val="0"/><w:marRight w:val="0"/><w:marTop w:val="0"/><w:marBottom w:val="0"/><w:divBdr><w:top w:val="none" w:sz="0" w:space="0" w:color="auto"/><w:left w:val="none" w:sz="0" w:space="0" w:color="auto"/><w:bottom w:val="none" w:sz="0" w:space="0" w:color="auto"/><w:right w:val="none" w:sz="0" w:space="0" w:color="auto"/></w:divBdr></w:div><w:div w:id="1706129672"><w:bodyDiv w:val="1"/><w:marLeft w:val="0"/><w:marRight w:val="0"/><w:marTop w:val="0"/><w:marBottom w:val="0"/><w:divBdr><w:top w:val="none" w:sz="0" w:space="0" w:color="auto"/><w:left w:val="none" w:sz="0" w:space="0" w:color="auto"/><w:bottom w:val="none" w:sz="0" w:space="0" w:color="auto"/><w:right w:val="none" w:sz="0" w:space="0" w:color="auto"/></w:divBdr><w:divsChild><w:div w:id="1476095500"><w:marLeft w:val="360"/><w:marRight w:val="0"/><w:marTop w:val="200"/><w:marBottom w:val="0"/><w:divBdr><w:top w:val="none" w:sz="0" w:space="0" w:color="auto"/><w:left w:val="none" w:sz="0" w:space="0" w:color="auto"/><w:bottom w:val="none" w:sz="0" w:space="0" w:color="auto"/><w:right w:val="none" w:sz="0" w:space="0" w:color="auto"/></w:divBdr></w:div></w:divsChild></w:div></w:divs><w:optimizeForBrowser/><w:relyOnVML/><w:allowPNG/></w:webSettings>