{
    "itemid": 3956081, 
    "clientabbr": "ELVR", 
    "basepath": "/apol23/PowerManage/ELVR/YSROE/YSROE_00_00/YSROE50950/", 
    "pcurl": null, 
    "clientid": 1722, 
    "lemans_figureCount": 0, 
    "stageid": 11, 
    "isLemoII": "0", 
    "title": "Hypersensitivity Pneumonitis: Imaging Findings and Patterns", 
    "isCbpWorkflow": 0, 
    "clientreference": "YSROE50950", 
    "noOfSuppliments": null, 
    "proofCreationProcess": "Classic", 
    "platform": "3B2", 
    "tsp": null, 
    "ceType": "2T", 
    "isProofCentral": "1", 
    "proofCentralLevel": "3.1", 
    "sourcefiletype": "DOCX", 
    "pc_counter": "1", 
    "hms": "1", 
    "inScope_Cpc": "N", 
    "lemans_figureDataArray": null, 
    "isLemo": "0", 
    "stage": "Galley", 
    "lemans_eComponentCount": 0, 
    "iscpc": "0", 
    "itemcpc": "N", 
    "lemans_ProductionType": null, 
    "currenttask": "Art Conversion", 
    "lemans_eComponentDataArray": null, 
    "noOfFigs": "8", 
    "proofPdf": "0", 
    "lemans_DocHead": "", 
    "lemans_PublicationItemType": null
}
